GitOS/EasyOS.py
GitOS/__init__.py
GitOS/main.py
GitOS-0.1.0.dist-info/LICENCE
GitOS-0.1.0.dist-info/METADATA
GitOS-0.1.0.dist-info/WHEEL
GitOS-0.1.0.dist-info/top_level.txt
GitOS-0.1.0.dist-info/RECORD
