Metadata-Version: 2.1
Name: GitOS
Version: 0.1.0
Summary: Package for Using Git and Colab and Drive
Home-page: https://github.com/rama96/GitOS.git
Author: Ramamurthi
Author-email: ramamurthi96@gmail.com
License: Apache License 2.0
Platform: UNKNOWN
Requires-Dist: numpy
Requires-Dist: pandas
